gardnersnake/__init__.py
gardnersnake/core/__init__.py
gardnersnake/core/config.py
gardnersnake/core/exceptions.py
scripts/__init__.py
scripts/check_directory.py
gardnersnake-0.4.1.7.dist-info/LICENSE
gardnersnake-0.4.1.7.dist-info/METADATA
gardnersnake-0.4.1.7.dist-info/WHEEL
gardnersnake-0.4.1.7.dist-info/entry_points.txt
gardnersnake-0.4.1.7.dist-info/top_level.txt
gardnersnake-0.4.1.7.dist-info/RECORD
