Metadata-Version: 2.1
Name: gardnersnake
Version: 0.4.1.7
Summary: Utilities for writing concise snakemake workflows
Home-page: https://github.com/zwebbs/gardnersnake
Author: Zach Weber
Author-email: zach.weber.813@gmail.com
Project-URL: Bug Tracker, https://github.com/zwebbs/gardnersnake/issues
Classifier: Programming Language :: Python :: 3
Classifier: License :: OSI Approved :: GNU Affero General Public License v3 or later (AGPLv3+)
Classifier: Operating System :: OS Independent
Requires-Python: >=3.7
License-File: LICENSE
Requires-Dist: pyyaml (==6.0)
